<?xml version="1.0" encoding="utf-8"?>
<BindInfo>
	<BindNode BINDTYPE="op" DISPLAY="bind_op add" ID="" IMPL="fabric" LATENCY="0" OPTYPE="add" PRAGMA="" RTLNAME="add_ln83_fu_94_p2" SOURCE="dlin.c:83" VARIABLE="add_ln83" MODULE="read_lin_reg_1" LOOP="" BUNDLEDNAME="" DSP="0" BRAM="0" URAM="0"/>
	<BindNode BINDTYPE="op" DISPLAY="bind_op add" ID="" IMPL="fabric" LATENCY="0" OPTYPE="add" PRAGMA="" RTLNAME="add_ln213_fu_122_p2" SOURCE="dlin.c:213" VARIABLE="add_ln213" MODULE="single_lin_process_1_Pipeline_VITIS_LOOP_213_1" LOOP="VITIS_LOOP_213_1" BUNDLEDNAME="" DSP="0" BRAM="0" URAM="0"/>
	<BindNode BINDTYPE="op" DISPLAY="bind_op icmp" ID="" IMPL="auto" LATENCY="0" OPTYPE="icmp" PRAGMA="" RTLNAME="icmp_ln213_fu_128_p2" SOURCE="dlin.c:213" VARIABLE="icmp_ln213" MODULE="single_lin_process_1_Pipeline_VITIS_LOOP_213_1" LOOP="VITIS_LOOP_213_1" BUNDLEDNAME="" DSP="0" BRAM="0" URAM="0"/>
	<BindNode BINDTYPE="op" DISPLAY="bind_op add" ID="" IMPL="fabric" LATENCY="0" OPTYPE="add" PRAGMA="" RTLNAME="add_ln213_1_fu_134_p2" SOURCE="dlin.c:213" VARIABLE="add_ln213_1" MODULE="single_lin_process_1_Pipeline_VITIS_LOOP_213_1" LOOP="VITIS_LOOP_213_1" BUNDLEDNAME="" DSP="0" BRAM="0" URAM="0"/>
	<BindNode BINDTYPE="storage" DISPLAY="bind_storage ram_s2p" ID="" IMPL="auto" LATENCY="1" OPTYPE="ram_s2p" PRAGMA="" RTLNAME="ringbuffer_header_bytes_U" SOURCE="dlin.c:95" VARIABLE="ringbuffer_header_bytes" MODULE="write_lin_ddr_1" LOOP="" BUNDLEDNAME="" DSP="0" BRAM="0" URAM="0"/>
	<BindNode BINDTYPE="op" DISPLAY="bind_op icmp" ID="" IMPL="auto" LATENCY="0" OPTYPE="icmp" PRAGMA="" RTLNAME="exitcond66_fu_354_p2" SOURCE="" VARIABLE="exitcond66" MODULE="write_lin_ddr_1" LOOP="Loop 1" BUNDLEDNAME="" DSP="0" BRAM="0" URAM="0"/>
	<BindNode BINDTYPE="op" DISPLAY="bind_op add" ID="" IMPL="fabric" LATENCY="0" OPTYPE="add" PRAGMA="" RTLNAME="empty_67_fu_360_p2" SOURCE="" VARIABLE="empty_67" MODULE="write_lin_ddr_1" LOOP="Loop 1" BUNDLEDNAME="" DSP="0" BRAM="0" URAM="0"/>
	<BindNode BINDTYPE="op" DISPLAY="bind_op add" ID="" IMPL="fabric" LATENCY="0" OPTYPE="add" PRAGMA="" RTLNAME="grp_fu_403_p0" SOURCE="dlin.c:113" VARIABLE="add_ln113" MODULE="write_lin_ddr_1" LOOP="" BUNDLEDNAME="" DSP="0" BRAM="0" URAM="0"/>
	<BindNode BINDTYPE="op" DISPLAY="bind_op urem" ID="" IMPL="auto_seq" LATENCY="35" OPTYPE="urem" PRAGMA="" RTLNAME="urem_32ns_32ns_32_36_seq_1_U10" SOURCE="dlin.c:113" VARIABLE="nextWriteLinIndex" MODULE="write_lin_ddr_1" LOOP="" BUNDLEDNAME="" DSP="0" BRAM="0" URAM="0"/>
	<BindNode BINDTYPE="op" DISPLAY="bind_op icmp" ID="" IMPL="auto" LATENCY="0" OPTYPE="icmp" PRAGMA="" RTLNAME="icmp_ln115_fu_421_p2" SOURCE="dlin.c:115" VARIABLE="icmp_ln115" MODULE="write_lin_ddr_1" LOOP="" BUNDLEDNAME="" DSP="0" BRAM="0" URAM="0"/>
	<BindNode BINDTYPE="op" DISPLAY="bind_op sub" ID="" IMPL="fabric" LATENCY="0" OPTYPE="sub" PRAGMA="" RTLNAME="sub_ln122_fu_459_p2" SOURCE="dlin.c:122" VARIABLE="sub_ln122" MODULE="write_lin_ddr_1" LOOP="" BUNDLEDNAME="" DSP="0" BRAM="0" URAM="0"/>
	<BindNode BINDTYPE="op" DISPLAY="bind_op all" ID="" IMPL="tadder" LATENCY="0" OPTYPE="all" PRAGMA="" RTLNAME="add_ln122_fu_465_p2" SOURCE="dlin.c:122" VARIABLE="add_ln122" MODULE="write_lin_ddr_1" LOOP="" BUNDLEDNAME="" DSP="0" BRAM="0" URAM="0"/>
	<BindNode BINDTYPE="op" DISPLAY="bind_op all" ID="" IMPL="tadder" LATENCY="0" OPTYPE="all" PRAGMA="" RTLNAME="add_ln122_1_fu_471_p2" SOURCE="dlin.c:122" VARIABLE="add_ln122_1" MODULE="write_lin_ddr_1" LOOP="" BUNDLEDNAME="" DSP="0" BRAM="0" URAM="0"/>
	<BindNode BINDTYPE="op" DISPLAY="bind_op icmp" ID="" IMPL="auto" LATENCY="0" OPTYPE="icmp" PRAGMA="" RTLNAME="exitcond55_fu_501_p2" SOURCE="" VARIABLE="exitcond55" MODULE="write_lin_ddr_1" LOOP="Loop 2" BUNDLEDNAME="" DSP="0" BRAM="0" URAM="0"/>
	<BindNode BINDTYPE="op" DISPLAY="bind_op add" ID="" IMPL="fabric" LATENCY="0" OPTYPE="add" PRAGMA="" RTLNAME="empty_70_fu_507_p2" SOURCE="" VARIABLE="empty_70" MODULE="write_lin_ddr_1" LOOP="Loop 2" BUNDLEDNAME="" DSP="0" BRAM="0" URAM="0"/>
	<BindNode BINDTYPE="op" DISPLAY="bind_op add" ID="" IMPL="fabric" LATENCY="0" OPTYPE="add" PRAGMA="" RTLNAME="add_ln17_fu_523_p2" SOURCE="clu.c:17" VARIABLE="add_ln17" MODULE="write_lin_ddr_1" LOOP="" BUNDLEDNAME="" DSP="0" BRAM="0" URAM="0"/>
	<BindNode BINDTYPE="op" DISPLAY="bind_op icmp" ID="" IMPL="auto" LATENCY="0" OPTYPE="icmp" PRAGMA="" RTLNAME="exitcond4_fu_572_p2" SOURCE="" VARIABLE="exitcond4" MODULE="write_lin_ddr_1" LOOP="Loop 3" BUNDLEDNAME="" DSP="0" BRAM="0" URAM="0"/>
	<BindNode BINDTYPE="op" DISPLAY="bind_op add" ID="" IMPL="fabric" LATENCY="0" OPTYPE="add" PRAGMA="" RTLNAME="empty_74_fu_578_p2" SOURCE="" VARIABLE="empty_74" MODULE="write_lin_ddr_1" LOOP="Loop 3" BUNDLEDNAME="" DSP="0" BRAM="0" URAM="0"/>
	<BindNode BINDTYPE="op" DISPLAY="bind_op mux" ID="" IMPL="auto" LATENCY="0" OPTYPE="mux" PRAGMA="" RTLNAME="mux_42_8_1_1_U11" SOURCE="clu.c:13" VARIABLE="tmp_6" MODULE="write_lin_ddr_1" LOOP="Loop 3" BUNDLEDNAME="" DSP="0" BRAM="0" URAM="0"/>
	<BindNode BINDTYPE="op" DISPLAY="bind_op add" ID="" IMPL="fabric" LATENCY="0" OPTYPE="add" PRAGMA="" RTLNAME="add_ln116_fu_611_p2" SOURCE="dlin.c:116" VARIABLE="add_ln116" MODULE="write_lin_ddr_1" LOOP="" BUNDLEDNAME="" DSP="0" BRAM="0" URAM="0"/>
	<BindNode BINDTYPE="op" DISPLAY="bind_op add" ID="" IMPL="fabric" LATENCY="0" OPTYPE="add" PRAGMA="" RTLNAME="add_ln117_1_fu_623_p2" SOURCE="dlin.c:117" VARIABLE="add_ln117_1" MODULE="write_lin_ddr_1" LOOP="" BUNDLEDNAME="" DSP="0" BRAM="0" URAM="0"/>
	<BindNode BINDTYPE="op" DISPLAY="bind_op add" ID="" IMPL="fabric" LATENCY="0" OPTYPE="add" PRAGMA="" RTLNAME="add_ln117_fu_487_p2" SOURCE="dlin.c:117" VARIABLE="add_ln117" MODULE="write_lin_ddr_1" LOOP="" BUNDLEDNAME="" DSP="0" BRAM="0" URAM="0"/>
	<BindNode BINDTYPE="storage" DISPLAY="bind_storage ram_t2p" ID="" IMPL="auto" LATENCY="1" OPTYPE="ram_t2p" PRAGMA="" RTLNAME="lin_frame_U" SOURCE="dlin.c:175" VARIABLE="lin_frame" MODULE="single_lin_process_1" LOOP="" BUNDLEDNAME="" DSP="0" BRAM="0" URAM="0"/>
	<BindNode BINDTYPE="op" DISPLAY="bind_op icmp" ID="" IMPL="auto" LATENCY="0" OPTYPE="icmp" PRAGMA="" RTLNAME="exitcond1_fu_887_p2" SOURCE="" VARIABLE="exitcond1" MODULE="single_lin_process_1" LOOP="Loop 1" BUNDLEDNAME="" DSP="0" BRAM="0" URAM="0"/>
	<BindNode BINDTYPE="op" DISPLAY="bind_op add" ID="" IMPL="fabric" LATENCY="0" OPTYPE="add" PRAGMA="" RTLNAME="empty_87_fu_893_p2" SOURCE="" VARIABLE="empty_87" MODULE="single_lin_process_1" LOOP="Loop 1" BUNDLEDNAME="" DSP="0" BRAM="0" URAM="0"/>
	<BindNode BINDTYPE="op" DISPLAY="bind_op add" ID="" IMPL="fabric" LATENCY="0" OPTYPE="add" PRAGMA="" RTLNAME="grp_fu_856_p2" SOURCE="dlin.c:89" VARIABLE="add_ln89" MODULE="single_lin_process_1" LOOP="" BUNDLEDNAME="" DSP="0" BRAM="0" URAM="0"/>
	<BindNode BINDTYPE="op" DISPLAY="bind_op add" ID="" IMPL="fabric" LATENCY="0" OPTYPE="add" PRAGMA="" RTLNAME="add_ln89_1_fu_942_p2" SOURCE="dlin.c:89" VARIABLE="add_ln89_1" MODULE="single_lin_process_1" LOOP="" BUNDLEDNAME="" DSP="0" BRAM="0" URAM="0"/>
	<BindNode BINDTYPE="op" DISPLAY="bind_op icmp" ID="" IMPL="auto" LATENCY="0" OPTYPE="icmp" PRAGMA="" RTLNAME="icmp_ln201_fu_926_p2" SOURCE="dlin.c:201" VARIABLE="icmp_ln201" MODULE="single_lin_process_1" LOOP="" BUNDLEDNAME="" DSP="0" BRAM="0" URAM="0"/>
	<BindNode BINDTYPE="op" DISPLAY="bind_op icmp" ID="" IMPL="auto" LATENCY="0" OPTYPE="icmp" PRAGMA="" RTLNAME="icmp_ln204_fu_987_p2" SOURCE="dlin.c:204" VARIABLE="icmp_ln204" MODULE="single_lin_process_1" LOOP="" BUNDLEDNAME="" DSP="0" BRAM="0" URAM="0"/>
	<BindNode BINDTYPE="op" DISPLAY="bind_op add" ID="" IMPL="fabric" LATENCY="0" OPTYPE="add" PRAGMA="" RTLNAME="grp_fu_856_p2" SOURCE="dlin.c:89" VARIABLE="add_ln89_2" MODULE="single_lin_process_1" LOOP="" BUNDLEDNAME="" DSP="0" BRAM="0" URAM="0"/>
	<BindNode BINDTYPE="op" DISPLAY="bind_op add" ID="" IMPL="fabric" LATENCY="0" OPTYPE="add" PRAGMA="" RTLNAME="add_ln230_fu_1094_p2" SOURCE="dlin.c:230" VARIABLE="add_ln230" MODULE="single_lin_process_1" LOOP="" BUNDLEDNAME="" DSP="0" BRAM="0" URAM="0"/>
	<BindNode BINDTYPE="op" DISPLAY="bind_op add" ID="" IMPL="fabric" LATENCY="0" OPTYPE="add" PRAGMA="" RTLNAME="add_ln271_fu_1162_p2" SOURCE="dlin.c:271" VARIABLE="add_ln271" MODULE="single_lin_process_1" LOOP="" BUNDLEDNAME="" DSP="0" BRAM="0" URAM="0"/>
	<BindNode BINDTYPE="op" DISPLAY="bind_op add" ID="" IMPL="fabric" LATENCY="0" OPTYPE="add" PRAGMA="" RTLNAME="add_ln267_fu_1174_p2" SOURCE="dlin.c:267" VARIABLE="add_ln267" MODULE="single_lin_process_1" LOOP="" BUNDLEDNAME="" DSP="0" BRAM="0" URAM="0"/>
	<BindNode BINDTYPE="op" DISPLAY="bind_op add" ID="" IMPL="fabric" LATENCY="0" OPTYPE="add" PRAGMA="" RTLNAME="add_ln263_fu_1186_p2" SOURCE="dlin.c:263" VARIABLE="add_ln263" MODULE="single_lin_process_1" LOOP="" BUNDLEDNAME="" DSP="0" BRAM="0" URAM="0"/>
	<BindNode BINDTYPE="op" DISPLAY="bind_op add" ID="" IMPL="fabric" LATENCY="0" OPTYPE="add" PRAGMA="" RTLNAME="add_ln259_fu_1198_p2" SOURCE="dlin.c:259" VARIABLE="add_ln259" MODULE="single_lin_process_1" LOOP="" BUNDLEDNAME="" DSP="0" BRAM="0" URAM="0"/>
	<BindNode BINDTYPE="op" DISPLAY="bind_op add" ID="" IMPL="fabric" LATENCY="0" OPTYPE="add" PRAGMA="" RTLNAME="add_ln255_fu_1210_p2" SOURCE="dlin.c:255" VARIABLE="add_ln255" MODULE="single_lin_process_1" LOOP="" BUNDLEDNAME="" DSP="0" BRAM="0" URAM="0"/>
	<BindNode BINDTYPE="op" DISPLAY="bind_op add" ID="" IMPL="fabric" LATENCY="0" OPTYPE="add" PRAGMA="" RTLNAME="add_ln251_fu_1222_p2" SOURCE="dlin.c:251" VARIABLE="add_ln251" MODULE="single_lin_process_1" LOOP="" BUNDLEDNAME="" DSP="0" BRAM="0" URAM="0"/>
	<BindNode BINDTYPE="op" DISPLAY="bind_op add" ID="" IMPL="fabric" LATENCY="0" OPTYPE="add" PRAGMA="" RTLNAME="add_ln247_fu_1234_p2" SOURCE="dlin.c:247" VARIABLE="add_ln247" MODULE="single_lin_process_1" LOOP="" BUNDLEDNAME="" DSP="0" BRAM="0" URAM="0"/>
	<BindNode BINDTYPE="op" DISPLAY="bind_op add" ID="" IMPL="fabric" LATENCY="0" OPTYPE="add" PRAGMA="" RTLNAME="add_ln243_fu_1246_p2" SOURCE="dlin.c:243" VARIABLE="add_ln243" MODULE="single_lin_process_1" LOOP="" BUNDLEDNAME="" DSP="0" BRAM="0" URAM="0"/>
	<BindNode BINDTYPE="op" DISPLAY="bind_op add" ID="" IMPL="fabric" LATENCY="0" OPTYPE="add" PRAGMA="" RTLNAME="add_ln275_fu_1258_p2" SOURCE="dlin.c:275" VARIABLE="add_ln275" MODULE="single_lin_process_1" LOOP="" BUNDLEDNAME="" DSP="0" BRAM="0" URAM="0"/>
	<BindNode BINDTYPE="op" DISPLAY="bind_op add" ID="" IMPL="fabric" LATENCY="0" OPTYPE="add" PRAGMA="" RTLNAME="add_ln239_fu_1270_p2" SOURCE="dlin.c:239" VARIABLE="add_ln239" MODULE="single_lin_process_1" LOOP="" BUNDLEDNAME="" DSP="0" BRAM="0" URAM="0"/>
	<BindNode BINDTYPE="op" DISPLAY="bind_op add" ID="" IMPL="fabric" LATENCY="0" OPTYPE="add" PRAGMA="" RTLNAME="received_lin" SOURCE="dlin.c:297" VARIABLE="add_ln297" MODULE="single_lin_process_1" LOOP="" BUNDLEDNAME="" DSP="0" BRAM="0" URAM="0"/>
	<BindNode BINDTYPE="storage" DISPLAY="bind_storage ram_1p" ID="" IMPL="auto" LATENCY="1" OPTYPE="ram_1p" PRAGMA="" RTLNAME="PLIN_Ctrl_run_state_U" SOURCE="" VARIABLE="PLIN_Ctrl_run_state" MODULE="single_lin_process_1" LOOP="" BUNDLEDNAME="" DSP="0" BRAM="0" URAM="0"/>
	<BindNode BINDTYPE="op" DISPLAY="bind_op icmp" ID="" IMPL="auto" LATENCY="0" OPTYPE="icmp" PRAGMA="" RTLNAME="exitcond193_fu_50_p2" SOURCE="" VARIABLE="exitcond193" MODULE="recvFrame_logic_1_Pipeline_1" LOOP="Loop 1" BUNDLEDNAME="" DSP="0" BRAM="0" URAM="0"/>
	<BindNode BINDTYPE="op" DISPLAY="bind_op add" ID="" IMPL="fabric" LATENCY="0" OPTYPE="add" PRAGMA="" RTLNAME="empty_91_fu_56_p2" SOURCE="" VARIABLE="empty_91" MODULE="recvFrame_logic_1_Pipeline_1" LOOP="Loop 1" BUNDLEDNAME="" DSP="0" BRAM="0" URAM="0"/>
	<BindNode BINDTYPE="op" DISPLAY="bind_op icmp" ID="" IMPL="auto" LATENCY="0" OPTYPE="icmp" PRAGMA="" RTLNAME="icmp_ln238_fu_184_p2" SOURCE="can.c:238" VARIABLE="icmp_ln238" MODULE="recvFrame_logic_1_Pipeline_VITIS_LOOP_238_2" LOOP="VITIS_LOOP_238_2" BUNDLEDNAME="" DSP="0" BRAM="0" URAM="0"/>
	<BindNode BINDTYPE="op" DISPLAY="bind_op add" ID="" IMPL="fabric" LATENCY="0" OPTYPE="add" PRAGMA="" RTLNAME="add_ln241_fu_190_p2" SOURCE="can.c:241" VARIABLE="add_ln241" MODULE="recvFrame_logic_1_Pipeline_VITIS_LOOP_238_2" LOOP="VITIS_LOOP_238_2" BUNDLEDNAME="" DSP="0" BRAM="0" URAM="0"/>
	<BindNode BINDTYPE="op" DISPLAY="bind_op sub" ID="" IMPL="fabric" LATENCY="0" OPTYPE="sub" PRAGMA="" RTLNAME="sub_ln241_fu_214_p2" SOURCE="can.c:241" VARIABLE="sub_ln241" MODULE="recvFrame_logic_1_Pipeline_VITIS_LOOP_238_2" LOOP="VITIS_LOOP_238_2" BUNDLEDNAME="" DSP="0" BRAM="0" URAM="0"/>
	<BindNode BINDTYPE="op" DISPLAY="bind_op sub" ID="" IMPL="fabric" LATENCY="0" OPTYPE="sub" PRAGMA="" RTLNAME="sub_ln241_1_fu_229_p2" SOURCE="can.c:241" VARIABLE="sub_ln241_1" MODULE="recvFrame_logic_1_Pipeline_VITIS_LOOP_238_2" LOOP="VITIS_LOOP_238_2" BUNDLEDNAME="" DSP="0" BRAM="0" URAM="0"/>
	<BindNode BINDTYPE="op" DISPLAY="bind_op select" ID="" IMPL="auto_sel" LATENCY="0" OPTYPE="select" PRAGMA="" RTLNAME="select_ln241_fu_244_p3" SOURCE="can.c:241" VARIABLE="select_ln241" MODULE="recvFrame_logic_1_Pipeline_VITIS_LOOP_238_2" LOOP="VITIS_LOOP_238_2" BUNDLEDNAME="" DSP="0" BRAM="0" URAM="0"/>
	<BindNode BINDTYPE="op" DISPLAY="bind_op add" ID="" IMPL="fabric" LATENCY="0" OPTYPE="add" PRAGMA="" RTLNAME="add_ln240_fu_260_p2" SOURCE="can.c:240" VARIABLE="add_ln240" MODULE="recvFrame_logic_1_Pipeline_VITIS_LOOP_238_2" LOOP="VITIS_LOOP_238_2" BUNDLEDNAME="" DSP="0" BRAM="0" URAM="0"/>
	<BindNode BINDTYPE="op" DISPLAY="bind_op add" ID="" IMPL="fabric" LATENCY="0" OPTYPE="add" PRAGMA="" RTLNAME="add_ln242_fu_326_p2" SOURCE="can.c:242" VARIABLE="add_ln242" MODULE="recvFrame_logic_1_Pipeline_VITIS_LOOP_238_2" LOOP="VITIS_LOOP_238_2" BUNDLEDNAME="" DSP="0" BRAM="0" URAM="0"/>
	<BindNode BINDTYPE="op" DISPLAY="bind_op add" ID="" IMPL="fabric" LATENCY="0" OPTYPE="add" PRAGMA="" RTLNAME="add_ln243_fu_337_p2" SOURCE="can.c:243" VARIABLE="add_ln243" MODULE="recvFrame_logic_1_Pipeline_VITIS_LOOP_238_2" LOOP="VITIS_LOOP_238_2" BUNDLEDNAME="" DSP="0" BRAM="0" URAM="0"/>
	<BindNode BINDTYPE="op" DISPLAY="bind_op add" ID="" IMPL="fabric" LATENCY="0" OPTYPE="add" PRAGMA="" RTLNAME="add_ln244_fu_359_p2" SOURCE="can.c:244" VARIABLE="add_ln244" MODULE="recvFrame_logic_1_Pipeline_VITIS_LOOP_238_2" LOOP="VITIS_LOOP_238_2" BUNDLEDNAME="" DSP="0" BRAM="0" URAM="0"/>
	<BindNode BINDTYPE="op" DISPLAY="bind_op add" ID="" IMPL="fabric" LATENCY="0" OPTYPE="add" PRAGMA="" RTLNAME="add_ln245_fu_369_p2" SOURCE="can.c:245" VARIABLE="add_ln245" MODULE="recvFrame_logic_1_Pipeline_VITIS_LOOP_238_2" LOOP="VITIS_LOOP_238_2" BUNDLEDNAME="" DSP="0" BRAM="0" URAM="0"/>
	<BindNode BINDTYPE="op" DISPLAY="bind_op add" ID="" IMPL="fabric" LATENCY="0" OPTYPE="add" PRAGMA="" RTLNAME="add_ln246_fu_348_p2" SOURCE="can.c:246" VARIABLE="add_ln246" MODULE="recvFrame_logic_1_Pipeline_VITIS_LOOP_238_2" LOOP="VITIS_LOOP_238_2" BUNDLEDNAME="" DSP="0" BRAM="0" URAM="0"/>
	<BindNode BINDTYPE="op" DISPLAY="bind_op add" ID="" IMPL="fabric" LATENCY="0" OPTYPE="add" PRAGMA="" RTLNAME="Len_3_fu_196_p2" SOURCE="can.c:238" VARIABLE="Len_3" MODULE="recvFrame_logic_1_Pipeline_VITIS_LOOP_238_2" LOOP="VITIS_LOOP_238_2" BUNDLEDNAME="" DSP="0" BRAM="0" URAM="0"/>
	<BindNode BINDTYPE="op" DISPLAY="bind_op icmp" ID="" IMPL="auto" LATENCY="0" OPTYPE="icmp" PRAGMA="" RTLNAME="icmp_ln223_fu_186_p2" SOURCE="can.c:223" VARIABLE="icmp_ln223" MODULE="recvFrame_logic_1_Pipeline_VITIS_LOOP_223_1" LOOP="VITIS_LOOP_223_1" BUNDLEDNAME="" DSP="0" BRAM="0" URAM="0"/>
	<BindNode BINDTYPE="op" DISPLAY="bind_op add" ID="" IMPL="fabric" LATENCY="0" OPTYPE="add" PRAGMA="" RTLNAME="DwIndex_2_fu_192_p2" SOURCE="can.c:233" VARIABLE="DwIndex_2" MODULE="recvFrame_logic_1_Pipeline_VITIS_LOOP_223_1" LOOP="VITIS_LOOP_223_1" BUNDLEDNAME="" DSP="0" BRAM="0" URAM="0"/>
	<BindNode BINDTYPE="op" DISPLAY="bind_op all" ID="" IMPL="tadder" LATENCY="0" OPTYPE="all" PRAGMA="" RTLNAME="add_ln226_1_fu_214_p2" SOURCE="can.c:226" VARIABLE="add_ln226_1" MODULE="recvFrame_logic_1_Pipeline_VITIS_LOOP_223_1" LOOP="VITIS_LOOP_223_1" BUNDLEDNAME="" DSP="0" BRAM="0" URAM="0"/>
	<BindNode BINDTYPE="op" DISPLAY="bind_op all" ID="" IMPL="tadder" LATENCY="0" OPTYPE="all" PRAGMA="" RTLNAME="add_ln226_fu_220_p2" SOURCE="can.c:226" VARIABLE="add_ln226" MODULE="recvFrame_logic_1_Pipeline_VITIS_LOOP_223_1" LOOP="VITIS_LOOP_223_1" BUNDLEDNAME="" DSP="0" BRAM="0" URAM="0"/>
	<BindNode BINDTYPE="op" DISPLAY="bind_op add" ID="" IMPL="fabric" LATENCY="0" OPTYPE="add" PRAGMA="" RTLNAME="add_ln228_fu_288_p2" SOURCE="can.c:228" VARIABLE="add_ln228" MODULE="recvFrame_logic_1_Pipeline_VITIS_LOOP_223_1" LOOP="VITIS_LOOP_223_1" BUNDLEDNAME="" DSP="0" BRAM="0" URAM="0"/>
	<BindNode BINDTYPE="op" DISPLAY="bind_op add" ID="" IMPL="fabric" LATENCY="0" OPTYPE="add" PRAGMA="" RTLNAME="add_ln229_fu_299_p2" SOURCE="can.c:229" VARIABLE="add_ln229" MODULE="recvFrame_logic_1_Pipeline_VITIS_LOOP_223_1" LOOP="VITIS_LOOP_223_1" BUNDLEDNAME="" DSP="0" BRAM="0" URAM="0"/>
	<BindNode BINDTYPE="op" DISPLAY="bind_op add" ID="" IMPL="fabric" LATENCY="0" OPTYPE="add" PRAGMA="" RTLNAME="add_ln230_fu_321_p2" SOURCE="can.c:230" VARIABLE="add_ln230" MODULE="recvFrame_logic_1_Pipeline_VITIS_LOOP_223_1" LOOP="VITIS_LOOP_223_1" BUNDLEDNAME="" DSP="0" BRAM="0" URAM="0"/>
	<BindNode BINDTYPE="op" DISPLAY="bind_op add" ID="" IMPL="fabric" LATENCY="0" OPTYPE="add" PRAGMA="" RTLNAME="add_ln231_fu_331_p2" SOURCE="can.c:231" VARIABLE="add_ln231" MODULE="recvFrame_logic_1_Pipeline_VITIS_LOOP_223_1" LOOP="VITIS_LOOP_223_1" BUNDLEDNAME="" DSP="0" BRAM="0" URAM="0"/>
	<BindNode BINDTYPE="op" DISPLAY="bind_op add" ID="" IMPL="fabric" LATENCY="0" OPTYPE="add" PRAGMA="" RTLNAME="add_ln232_fu_310_p2" SOURCE="can.c:232" VARIABLE="add_ln232" MODULE="recvFrame_logic_1_Pipeline_VITIS_LOOP_223_1" LOOP="VITIS_LOOP_223_1" BUNDLEDNAME="" DSP="0" BRAM="0" URAM="0"/>
	<BindNode BINDTYPE="op" DISPLAY="bind_op icmp" ID="" IMPL="auto" LATENCY="0" OPTYPE="icmp" PRAGMA="" RTLNAME="exitcond55_fu_91_p2" SOURCE="" VARIABLE="exitcond55" MODULE="write_ddr_1_Pipeline_1" LOOP="Loop 1" BUNDLEDNAME="" DSP="0" BRAM="0" URAM="0"/>
	<BindNode BINDTYPE="op" DISPLAY="bind_op add" ID="" IMPL="fabric" LATENCY="0" OPTYPE="add" PRAGMA="" RTLNAME="empty_79_fu_97_p2" SOURCE="" VARIABLE="empty_79" MODULE="write_ddr_1_Pipeline_1" LOOP="Loop 1" BUNDLEDNAME="" DSP="0" BRAM="0" URAM="0"/>
	<BindNode BINDTYPE="op" DISPLAY="bind_op icmp" ID="" IMPL="auto" LATENCY="0" OPTYPE="icmp" PRAGMA="" RTLNAME="exitcond4_fu_112_p2" SOURCE="" VARIABLE="exitcond4" MODULE="write_ddr_1_Pipeline_2" LOOP="Loop 1" BUNDLEDNAME="" DSP="0" BRAM="0" URAM="0"/>
	<BindNode BINDTYPE="op" DISPLAY="bind_op add" ID="" IMPL="fabric" LATENCY="0" OPTYPE="add" PRAGMA="" RTLNAME="empty_77_fu_118_p2" SOURCE="" VARIABLE="empty_77" MODULE="write_ddr_1_Pipeline_2" LOOP="Loop 1" BUNDLEDNAME="" DSP="0" BRAM="0" URAM="0"/>
	<BindNode BINDTYPE="op" DISPLAY="bind_op mux" ID="" IMPL="auto" LATENCY="0" OPTYPE="mux" PRAGMA="" RTLNAME="mux_42_8_1_1_U52" SOURCE="" VARIABLE="tmp_s" MODULE="write_ddr_1_Pipeline_2" LOOP="Loop 1" BUNDLEDNAME="" DSP="0" BRAM="0" URAM="0"/>
	<BindNode BINDTYPE="storage" DISPLAY="bind_storage ram_s2p" ID="" IMPL="auto" LATENCY="1" OPTYPE="ram_s2p" PRAGMA="" RTLNAME="ringbuffer_header_bytes_U" SOURCE="can.c:100" VARIABLE="ringbuffer_header_bytes" MODULE="write_ddr_1" LOOP="" BUNDLEDNAME="" DSP="0" BRAM="0" URAM="0"/>
	<BindNode BINDTYPE="op" DISPLAY="bind_op icmp" ID="" IMPL="auto" LATENCY="0" OPTYPE="icmp" PRAGMA="" RTLNAME="exitcond66_fu_317_p2" SOURCE="" VARIABLE="exitcond66" MODULE="write_ddr_1" LOOP="Loop 1" BUNDLEDNAME="" DSP="0" BRAM="0" URAM="0"/>
	<BindNode BINDTYPE="op" DISPLAY="bind_op add" ID="" IMPL="fabric" LATENCY="0" OPTYPE="add" PRAGMA="" RTLNAME="empty_81_fu_323_p2" SOURCE="" VARIABLE="empty_81" MODULE="write_ddr_1" LOOP="Loop 1" BUNDLEDNAME="" DSP="0" BRAM="0" URAM="0"/>
	<BindNode BINDTYPE="op" DISPLAY="bind_op add" ID="" IMPL="fabric" LATENCY="0" OPTYPE="add" PRAGMA="" RTLNAME="grp_fu_364_p0" SOURCE="can.c:116" VARIABLE="add_ln116" MODULE="write_ddr_1" LOOP="" BUNDLEDNAME="" DSP="0" BRAM="0" URAM="0"/>
	<BindNode BINDTYPE="op" DISPLAY="bind_op urem" ID="" IMPL="auto_seq" LATENCY="35" OPTYPE="urem" PRAGMA="" RTLNAME="urem_32ns_32ns_32_36_seq_1_U59" SOURCE="can.c:116" VARIABLE="nextWriteCanIndex" MODULE="write_ddr_1" LOOP="" BUNDLEDNAME="" DSP="0" BRAM="0" URAM="0"/>
	<BindNode BINDTYPE="op" DISPLAY="bind_op icmp" ID="" IMPL="auto" LATENCY="0" OPTYPE="icmp" PRAGMA="" RTLNAME="icmp_ln118_fu_382_p2" SOURCE="can.c:118" VARIABLE="icmp_ln118" MODULE="write_ddr_1" LOOP="" BUNDLEDNAME="" DSP="0" BRAM="0" URAM="0"/>
	<BindNode BINDTYPE="op" DISPLAY="bind_op mul" ID="" IMPL="auto" LATENCY="0" OPTYPE="mul" PRAGMA="" RTLNAME="mul_32s_8ns_32_1_1_U60" SOURCE="can.c:126" VARIABLE="mul_ln126" MODULE="write_ddr_1" LOOP="" BUNDLEDNAME="" DSP="1" BRAM="0" URAM="0"/>
	<BindNode BINDTYPE="op" DISPLAY="bind_op all" ID="" IMPL="tadder" LATENCY="0" OPTYPE="all" PRAGMA="" RTLNAME="add_ln126_fu_404_p2" SOURCE="can.c:126" VARIABLE="add_ln126" MODULE="write_ddr_1" LOOP="" BUNDLEDNAME="" DSP="0" BRAM="0" URAM="0"/>
	<BindNode BINDTYPE="op" DISPLAY="bind_op all" ID="" IMPL="tadder" LATENCY="0" OPTYPE="all" PRAGMA="" RTLNAME="add_ln126_1_fu_409_p2" SOURCE="can.c:126" VARIABLE="add_ln126_1" MODULE="write_ddr_1" LOOP="" BUNDLEDNAME="" DSP="0" BRAM="0" URAM="0"/>
	<BindNode BINDTYPE="op" DISPLAY="bind_op add" ID="" IMPL="fabric" LATENCY="0" OPTYPE="add" PRAGMA="" RTLNAME="add_ln17_fu_420_p2" SOURCE="clu.c:17" VARIABLE="add_ln17" MODULE="write_ddr_1" LOOP="" BUNDLEDNAME="" DSP="0" BRAM="0" URAM="0"/>
	<BindNode BINDTYPE="op" DISPLAY="bind_op add" ID="" IMPL="fabric" LATENCY="0" OPTYPE="add" PRAGMA="" RTLNAME="add_ln119_fu_473_p2" SOURCE="can.c:119" VARIABLE="add_ln119" MODULE="write_ddr_1" LOOP="" BUNDLEDNAME="" DSP="0" BRAM="0" URAM="0"/>
	<BindNode BINDTYPE="op" DISPLAY="bind_op add" ID="" IMPL="fabric" LATENCY="0" OPTYPE="add" PRAGMA="" RTLNAME="add_ln120_1_fu_485_p2" SOURCE="can.c:120" VARIABLE="add_ln120_1" MODULE="write_ddr_1" LOOP="" BUNDLEDNAME="" DSP="0" BRAM="0" URAM="0"/>
	<BindNode BINDTYPE="op" DISPLAY="bind_op add" ID="" IMPL="fabric" LATENCY="0" OPTYPE="add" PRAGMA="" RTLNAME="add_ln120_fu_393_p2" SOURCE="can.c:120" VARIABLE="add_ln120" MODULE="write_ddr_1" LOOP="" BUNDLEDNAME="" DSP="0" BRAM="0" URAM="0"/>
	<BindNode BINDTYPE="storage" DISPLAY="bind_storage ram_t2p" ID="" IMPL="auto" LATENCY="1" OPTYPE="ram_t2p" PRAGMA="" RTLNAME="can_frame_U" SOURCE="can.c:166" VARIABLE="can_frame" MODULE="recvFrame_logic_1" LOOP="" BUNDLEDNAME="" DSP="0" BRAM="0" URAM="0"/>
	<BindNode BINDTYPE="op" DISPLAY="bind_op add" ID="" IMPL="fabric" LATENCY="0" OPTYPE="add" PRAGMA="" RTLNAME="add_ln168_2_fu_723_p2" SOURCE="can.c:168" VARIABLE="add_ln168_2" MODULE="recvFrame_logic_1" LOOP="" BUNDLEDNAME="" DSP="0" BRAM="0" URAM="0"/>
	<BindNode BINDTYPE="op" DISPLAY="bind_op add" ID="" IMPL="fabric" LATENCY="0" OPTYPE="add" PRAGMA="" RTLNAME="add_ln168_fu_729_p2" SOURCE="can.c:168" VARIABLE="add_ln168" MODULE="recvFrame_logic_1" LOOP="" BUNDLEDNAME="" DSP="0" BRAM="0" URAM="0"/>
	<BindNode BINDTYPE="op" DISPLAY="bind_op add" ID="" IMPL="fabric" LATENCY="0" OPTYPE="add" PRAGMA="" RTLNAME="add_ln168_1_fu_757_p2" SOURCE="can.c:168" VARIABLE="add_ln168_1" MODULE="recvFrame_logic_1" LOOP="" BUNDLEDNAME="" DSP="0" BRAM="0" URAM="0"/>
	<BindNode BINDTYPE="op" DISPLAY="bind_op select" ID="" IMPL="auto_sel" LATENCY="0" OPTYPE="select" PRAGMA="" RTLNAME="select_ln176_fu_979_p3" SOURCE="can.c:176" VARIABLE="select_ln176" MODULE="recvFrame_logic_1" LOOP="" BUNDLEDNAME="" DSP="0" BRAM="0" URAM="0"/>
	<BindNode BINDTYPE="op" DISPLAY="bind_op select" ID="" IMPL="auto_sel" LATENCY="0" OPTYPE="select" PRAGMA="" RTLNAME="FrameID_1_fu_984_p3" SOURCE="can.c:172" VARIABLE="FrameID_1" MODULE="recvFrame_logic_1" LOOP="" BUNDLEDNAME="" DSP="0" BRAM="0" URAM="0"/>
	<BindNode BINDTYPE="op" DISPLAY="bind_op add" ID="" IMPL="fabric" LATENCY="0" OPTYPE="add" PRAGMA="" RTLNAME="add_ln191_fu_783_p2" SOURCE="can.c:191" VARIABLE="add_ln191" MODULE="recvFrame_logic_1" LOOP="" BUNDLEDNAME="" DSP="0" BRAM="0" URAM="0"/>
	<BindNode BINDTYPE="op" DISPLAY="bind_op add" ID="" IMPL="fabric" LATENCY="0" OPTYPE="add" PRAGMA="" RTLNAME="add_ln191_1_fu_810_p2" SOURCE="can.c:191" VARIABLE="add_ln191_1" MODULE="recvFrame_logic_1" LOOP="" BUNDLEDNAME="" DSP="0" BRAM="0" URAM="0"/>
	<BindNode BINDTYPE="op" DISPLAY="bind_op xor" ID="" IMPL="auto" LATENCY="0" OPTYPE="xor" PRAGMA="" RTLNAME="xor_ln28_fu_1059_p2" SOURCE="can.c:28" VARIABLE="xor_ln28" MODULE="recvFrame_logic_1" LOOP="" BUNDLEDNAME="" DSP="0" BRAM="0" URAM="0"/>
	<BindNode BINDTYPE="op" DISPLAY="bind_op icmp" ID="" IMPL="auto" LATENCY="0" OPTYPE="icmp" PRAGMA="" RTLNAME="icmp_ln28_fu_1064_p2" SOURCE="can.c:28" VARIABLE="icmp_ln28" MODULE="recvFrame_logic_1" LOOP="" BUNDLEDNAME="" DSP="0" BRAM="0" URAM="0"/>
	<BindNode BINDTYPE="op" DISPLAY="bind_op and" ID="" IMPL="auto" LATENCY="0" OPTYPE="and" PRAGMA="" RTLNAME="and_ln28_fu_1069_p2" SOURCE="can.c:28" VARIABLE="and_ln28" MODULE="recvFrame_logic_1" LOOP="" BUNDLEDNAME="" DSP="0" BRAM="0" URAM="0"/>
	<BindNode BINDTYPE="op" DISPLAY="bind_op select" ID="" IMPL="auto_sel" LATENCY="0" OPTYPE="select" PRAGMA="" RTLNAME="select_ln28_fu_1075_p3" SOURCE="can.c:28" VARIABLE="select_ln28" MODULE="recvFrame_logic_1" LOOP="" BUNDLEDNAME="" DSP="0" BRAM="0" URAM="0"/>
	<BindNode BINDTYPE="op" DISPLAY="bind_op icmp" ID="" IMPL="auto" LATENCY="0" OPTYPE="icmp" PRAGMA="" RTLNAME="icmp_ln32_fu_1083_p2" SOURCE="can.c:32" VARIABLE="icmp_ln32" MODULE="recvFrame_logic_1" LOOP="" BUNDLEDNAME="" DSP="0" BRAM="0" URAM="0"/>
	<BindNode BINDTYPE="op" DISPLAY="bind_op icmp" ID="" IMPL="auto" LATENCY="0" OPTYPE="icmp" PRAGMA="" RTLNAME="icmp_ln32_1_fu_1093_p2" SOURCE="can.c:32" VARIABLE="icmp_ln32_1" MODULE="recvFrame_logic_1" LOOP="" BUNDLEDNAME="" DSP="0" BRAM="0" URAM="0"/>
	<BindNode BINDTYPE="op" DISPLAY="bind_op icmp" ID="" IMPL="auto" LATENCY="0" OPTYPE="icmp" PRAGMA="" RTLNAME="icmp_ln32_2_fu_1099_p2" SOURCE="can.c:32" VARIABLE="icmp_ln32_2" MODULE="recvFrame_logic_1" LOOP="" BUNDLEDNAME="" DSP="0" BRAM="0" URAM="0"/>
	<BindNode BINDTYPE="op" DISPLAY="bind_op select" ID="" IMPL="auto_sel" LATENCY="0" OPTYPE="select" PRAGMA="" RTLNAME="select_ln32_fu_1105_p3" SOURCE="can.c:32" VARIABLE="select_ln32" MODULE="recvFrame_logic_1" LOOP="" BUNDLEDNAME="" DSP="0" BRAM="0" URAM="0"/>
	<BindNode BINDTYPE="op" DISPLAY="bind_op or" ID="" IMPL="auto" LATENCY="0" OPTYPE="or" PRAGMA="" RTLNAME="or_ln32_fu_1113_p2" SOURCE="can.c:32" VARIABLE="or_ln32" MODULE="recvFrame_logic_1" LOOP="" BUNDLEDNAME="" DSP="0" BRAM="0" URAM="0"/>
	<BindNode BINDTYPE="op" DISPLAY="bind_op select" ID="" IMPL="auto_sel" LATENCY="0" OPTYPE="select" PRAGMA="" RTLNAME="select_ln32_1_fu_1119_p3" SOURCE="can.c:32" VARIABLE="select_ln32_1" MODULE="recvFrame_logic_1" LOOP="" BUNDLEDNAME="" DSP="0" BRAM="0" URAM="0"/>
	<BindNode BINDTYPE="op" DISPLAY="bind_op icmp" ID="" IMPL="auto" LATENCY="0" OPTYPE="icmp" PRAGMA="" RTLNAME="icmp_ln32_3_fu_1131_p2" SOURCE="can.c:32" VARIABLE="icmp_ln32_3" MODULE="recvFrame_logic_1" LOOP="" BUNDLEDNAME="" DSP="0" BRAM="0" URAM="0"/>
	<BindNode BINDTYPE="op" DISPLAY="bind_op icmp" ID="" IMPL="auto" LATENCY="0" OPTYPE="icmp" PRAGMA="" RTLNAME="icmp_ln32_4_fu_1137_p2" SOURCE="can.c:32" VARIABLE="icmp_ln32_4" MODULE="recvFrame_logic_1" LOOP="" BUNDLEDNAME="" DSP="0" BRAM="0" URAM="0"/>
	<BindNode BINDTYPE="op" DISPLAY="bind_op select" ID="" IMPL="auto_sel" LATENCY="0" OPTYPE="select" PRAGMA="" RTLNAME="select_ln32_2_fu_1143_p3" SOURCE="can.c:32" VARIABLE="select_ln32_2" MODULE="recvFrame_logic_1" LOOP="" BUNDLEDNAME="" DSP="0" BRAM="0" URAM="0"/>
	<BindNode BINDTYPE="op" DISPLAY="bind_op or" ID="" IMPL="auto" LATENCY="0" OPTYPE="or" PRAGMA="" RTLNAME="or_ln32_1_fu_1151_p2" SOURCE="can.c:32" VARIABLE="or_ln32_1" MODULE="recvFrame_logic_1" LOOP="" BUNDLEDNAME="" DSP="0" BRAM="0" URAM="0"/>
	<BindNode BINDTYPE="op" DISPLAY="bind_op select" ID="" IMPL="auto_sel" LATENCY="0" OPTYPE="select" PRAGMA="" RTLNAME="select_ln32_3_fu_1157_p3" SOURCE="can.c:32" VARIABLE="select_ln32_3" MODULE="recvFrame_logic_1" LOOP="" BUNDLEDNAME="" DSP="0" BRAM="0" URAM="0"/>
	<BindNode BINDTYPE="op" DISPLAY="bind_op icmp" ID="" IMPL="auto" LATENCY="0" OPTYPE="icmp" PRAGMA="" RTLNAME="icmp_ln32_5_fu_1165_p2" SOURCE="can.c:32" VARIABLE="icmp_ln32_5" MODULE="recvFrame_logic_1" LOOP="" BUNDLEDNAME="" DSP="0" BRAM="0" URAM="0"/>
	<BindNode BINDTYPE="op" DISPLAY="bind_op icmp" ID="" IMPL="auto" LATENCY="0" OPTYPE="icmp" PRAGMA="" RTLNAME="icmp_ln32_6_fu_1171_p2" SOURCE="can.c:32" VARIABLE="icmp_ln32_6" MODULE="recvFrame_logic_1" LOOP="" BUNDLEDNAME="" DSP="0" BRAM="0" URAM="0"/>
	<BindNode BINDTYPE="op" DISPLAY="bind_op select" ID="" IMPL="auto_sel" LATENCY="0" OPTYPE="select" PRAGMA="" RTLNAME="select_ln32_4_fu_1177_p3" SOURCE="can.c:32" VARIABLE="select_ln32_4" MODULE="recvFrame_logic_1" LOOP="" BUNDLEDNAME="" DSP="0" BRAM="0" URAM="0"/>
	<BindNode BINDTYPE="op" DISPLAY="bind_op or" ID="" IMPL="auto" LATENCY="0" OPTYPE="or" PRAGMA="" RTLNAME="or_ln32_2_fu_1185_p2" SOURCE="can.c:32" VARIABLE="or_ln32_2" MODULE="recvFrame_logic_1" LOOP="" BUNDLEDNAME="" DSP="0" BRAM="0" URAM="0"/>
	<BindNode BINDTYPE="op" DISPLAY="bind_op select" ID="" IMPL="auto_sel" LATENCY="0" OPTYPE="select" PRAGMA="" RTLNAME="select_ln32_5_fu_1191_p3" SOURCE="can.c:32" VARIABLE="select_ln32_5" MODULE="recvFrame_logic_1" LOOP="" BUNDLEDNAME="" DSP="0" BRAM="0" URAM="0"/>
	<BindNode BINDTYPE="op" DISPLAY="bind_op icmp" ID="" IMPL="auto" LATENCY="0" OPTYPE="icmp" PRAGMA="" RTLNAME="icmp_ln32_7_fu_1199_p2" SOURCE="can.c:32" VARIABLE="icmp_ln32_7" MODULE="recvFrame_logic_1" LOOP="" BUNDLEDNAME="" DSP="0" BRAM="0" URAM="0"/>
	<BindNode BINDTYPE="op" DISPLAY="bind_op icmp" ID="" IMPL="auto" LATENCY="0" OPTYPE="icmp" PRAGMA="" RTLNAME="icmp_ln32_8_fu_1205_p2" SOURCE="can.c:32" VARIABLE="icmp_ln32_8" MODULE="recvFrame_logic_1" LOOP="" BUNDLEDNAME="" DSP="0" BRAM="0" URAM="0"/>
	<BindNode BINDTYPE="op" DISPLAY="bind_op select" ID="" IMPL="auto_sel" LATENCY="0" OPTYPE="select" PRAGMA="" RTLNAME="select_ln32_6_fu_1250_p3" SOURCE="can.c:32" VARIABLE="select_ln32_6" MODULE="recvFrame_logic_1" LOOP="" BUNDLEDNAME="" DSP="0" BRAM="0" URAM="0"/>
	<BindNode BINDTYPE="op" DISPLAY="bind_op or" ID="" IMPL="auto" LATENCY="0" OPTYPE="or" PRAGMA="" RTLNAME="or_ln32_3_fu_1257_p2" SOURCE="can.c:32" VARIABLE="or_ln32_3" MODULE="recvFrame_logic_1" LOOP="" BUNDLEDNAME="" DSP="0" BRAM="0" URAM="0"/>
	<BindNode BINDTYPE="op" DISPLAY="bind_op select" ID="" IMPL="auto_sel" LATENCY="0" OPTYPE="select" PRAGMA="" RTLNAME="select_ln32_7_fu_1261_p3" SOURCE="can.c:32" VARIABLE="select_ln32_7" MODULE="recvFrame_logic_1" LOOP="" BUNDLEDNAME="" DSP="0" BRAM="0" URAM="0"/>
	<BindNode BINDTYPE="op" DISPLAY="bind_op icmp" ID="" IMPL="auto" LATENCY="0" OPTYPE="icmp" PRAGMA="" RTLNAME="icmp_ln32_9_fu_1211_p2" SOURCE="can.c:32" VARIABLE="icmp_ln32_9" MODULE="recvFrame_logic_1" LOOP="" BUNDLEDNAME="" DSP="0" BRAM="0" URAM="0"/>
	<BindNode BINDTYPE="op" DISPLAY="bind_op icmp" ID="" IMPL="auto" LATENCY="0" OPTYPE="icmp" PRAGMA="" RTLNAME="icmp_ln32_10_fu_1217_p2" SOURCE="can.c:32" VARIABLE="icmp_ln32_10" MODULE="recvFrame_logic_1" LOOP="" BUNDLEDNAME="" DSP="0" BRAM="0" URAM="0"/>
	<BindNode BINDTYPE="op" DISPLAY="bind_op select" ID="" IMPL="auto_sel" LATENCY="0" OPTYPE="select" PRAGMA="" RTLNAME="select_ln32_8_fu_1273_p3" SOURCE="can.c:32" VARIABLE="select_ln32_8" MODULE="recvFrame_logic_1" LOOP="" BUNDLEDNAME="" DSP="0" BRAM="0" URAM="0"/>
	<BindNode BINDTYPE="op" DISPLAY="bind_op or" ID="" IMPL="auto" LATENCY="0" OPTYPE="or" PRAGMA="" RTLNAME="or_ln32_4_fu_1280_p2" SOURCE="can.c:32" VARIABLE="or_ln32_4" MODULE="recvFrame_logic_1" LOOP="" BUNDLEDNAME="" DSP="0" BRAM="0" URAM="0"/>
	<BindNode BINDTYPE="op" DISPLAY="bind_op select" ID="" IMPL="auto_sel" LATENCY="0" OPTYPE="select" PRAGMA="" RTLNAME="select_ln32_9_fu_1284_p3" SOURCE="can.c:32" VARIABLE="select_ln32_9" MODULE="recvFrame_logic_1" LOOP="" BUNDLEDNAME="" DSP="0" BRAM="0" URAM="0"/>
	<BindNode BINDTYPE="op" DISPLAY="bind_op icmp" ID="" IMPL="auto" LATENCY="0" OPTYPE="icmp" PRAGMA="" RTLNAME="icmp_ln32_11_fu_1223_p2" SOURCE="can.c:32" VARIABLE="icmp_ln32_11" MODULE="recvFrame_logic_1" LOOP="" BUNDLEDNAME="" DSP="0" BRAM="0" URAM="0"/>
	<BindNode BINDTYPE="op" DISPLAY="bind_op icmp" ID="" IMPL="auto" LATENCY="0" OPTYPE="icmp" PRAGMA="" RTLNAME="icmp_ln32_12_fu_1229_p2" SOURCE="can.c:32" VARIABLE="icmp_ln32_12" MODULE="recvFrame_logic_1" LOOP="" BUNDLEDNAME="" DSP="0" BRAM="0" URAM="0"/>
	<BindNode BINDTYPE="op" DISPLAY="bind_op select" ID="" IMPL="auto_sel" LATENCY="0" OPTYPE="select" PRAGMA="" RTLNAME="select_ln32_10_fu_1296_p3" SOURCE="can.c:32" VARIABLE="select_ln32_10" MODULE="recvFrame_logic_1" LOOP="" BUNDLEDNAME="" DSP="0" BRAM="0" URAM="0"/>
	<BindNode BINDTYPE="op" DISPLAY="bind_op or" ID="" IMPL="auto" LATENCY="0" OPTYPE="or" PRAGMA="" RTLNAME="or_ln32_5_fu_1303_p2" SOURCE="can.c:32" VARIABLE="or_ln32_5" MODULE="recvFrame_logic_1" LOOP="" BUNDLEDNAME="" DSP="0" BRAM="0" URAM="0"/>
	<BindNode BINDTYPE="op" DISPLAY="bind_op select" ID="" IMPL="auto_sel" LATENCY="0" OPTYPE="select" PRAGMA="" RTLNAME="select_ln32_11_fu_1307_p3" SOURCE="can.c:32" VARIABLE="select_ln32_11" MODULE="recvFrame_logic_1" LOOP="" BUNDLEDNAME="" DSP="0" BRAM="0" URAM="0"/>
	<BindNode BINDTYPE="op" DISPLAY="bind_op icmp" ID="" IMPL="auto" LATENCY="0" OPTYPE="icmp" PRAGMA="" RTLNAME="icmp_ln32_13_fu_1235_p2" SOURCE="can.c:32" VARIABLE="icmp_ln32_13" MODULE="recvFrame_logic_1" LOOP="" BUNDLEDNAME="" DSP="0" BRAM="0" URAM="0"/>
	<BindNode BINDTYPE="op" DISPLAY="bind_op icmp" ID="" IMPL="auto" LATENCY="0" OPTYPE="icmp" PRAGMA="" RTLNAME="icmp_ln32_14_fu_1241_p2" SOURCE="can.c:32" VARIABLE="icmp_ln32_14" MODULE="recvFrame_logic_1" LOOP="" BUNDLEDNAME="" DSP="0" BRAM="0" URAM="0"/>
	<BindNode BINDTYPE="op" DISPLAY="bind_op select" ID="" IMPL="auto_sel" LATENCY="0" OPTYPE="select" PRAGMA="" RTLNAME="empty_fu_1319_p3" SOURCE="can.c:32" VARIABLE="empty" MODULE="recvFrame_logic_1" LOOP="" BUNDLEDNAME="" DSP="0" BRAM="0" URAM="0"/>
	<BindNode BINDTYPE="op" DISPLAY="bind_op or" ID="" IMPL="auto" LATENCY="0" OPTYPE="or" PRAGMA="" RTLNAME="empty_92_fu_1326_p2" SOURCE="can.c:32" VARIABLE="empty_92" MODULE="recvFrame_logic_1" LOOP="" BUNDLEDNAME="" DSP="0" BRAM="0" URAM="0"/>
	<BindNode BINDTYPE="op" DISPLAY="bind_op select" ID="" IMPL="auto_sel" LATENCY="0" OPTYPE="select" PRAGMA="" RTLNAME="NofBytes_fu_1330_p3" SOURCE="can.c:214" VARIABLE="NofBytes" MODULE="recvFrame_logic_1" LOOP="" BUNDLEDNAME="" DSP="0" BRAM="0" URAM="0"/>
	<BindNode BINDTYPE="op" DISPLAY="bind_op add" ID="" IMPL="fabric" LATENCY="0" OPTYPE="add" PRAGMA="" RTLNAME="id_can_fu_915_p2" SOURCE="can.c:197" VARIABLE="id_can" MODULE="recvFrame_logic_1" LOOP="" BUNDLEDNAME="" DSP="0" BRAM="0" URAM="0"/>
	<BindNode BINDTYPE="op" DISPLAY="bind_op add" ID="" IMPL="fabric" LATENCY="0" OPTYPE="add" PRAGMA="" RTLNAME="add_ln214_fu_1347_p2" SOURCE="can.c:214" VARIABLE="add_ln214" MODULE="recvFrame_logic_1" LOOP="" BUNDLEDNAME="" DSP="0" BRAM="0" URAM="0"/>
	<BindNode BINDTYPE="op" DISPLAY="bind_op add" ID="" IMPL="fabric" LATENCY="0" OPTYPE="add" PRAGMA="" RTLNAME="add115_fu_1358_p2" SOURCE="can.c:168" VARIABLE="add115" MODULE="recvFrame_logic_1" LOOP="" BUNDLEDNAME="" DSP="0" BRAM="0" URAM="0"/>
	<BindNode BINDTYPE="op" DISPLAY="bind_op icmp" ID="" IMPL="auto" LATENCY="0" OPTYPE="icmp" PRAGMA="" RTLNAME="icmp_ln223_fu_1363_p2" SOURCE="can.c:223" VARIABLE="icmp_ln223" MODULE="recvFrame_logic_1" LOOP="" BUNDLEDNAME="" DSP="0" BRAM="0" URAM="0"/>
	<BindNode BINDTYPE="op" DISPLAY="bind_op add" ID="" IMPL="fabric" LATENCY="0" OPTYPE="add" PRAGMA="" RTLNAME="add_ln223_fu_1369_p2" SOURCE="can.c:223" VARIABLE="add_ln223" MODULE="recvFrame_logic_1" LOOP="" BUNDLEDNAME="" DSP="0" BRAM="0" URAM="0"/>
	<BindNode BINDTYPE="op" DISPLAY="bind_op add" ID="" IMPL="fabric" LATENCY="0" OPTYPE="add" PRAGMA="" RTLNAME="add_ln223_1_fu_1500_p2" SOURCE="can.c:223" VARIABLE="add_ln223_1" MODULE="recvFrame_logic_1" LOOP="" BUNDLEDNAME="" DSP="0" BRAM="0" URAM="0"/>
	<BindNode BINDTYPE="op" DISPLAY="bind_op add" ID="" IMPL="fabric" LATENCY="0" OPTYPE="add" PRAGMA="" RTLNAME="add_ln265_fu_1405_p2" SOURCE="can.c:265" VARIABLE="add_ln265" MODULE="recvFrame_logic_1" LOOP="" BUNDLEDNAME="" DSP="0" BRAM="0" URAM="0"/>
	<BindNode BINDTYPE="op" DISPLAY="bind_op add" ID="" IMPL="fabric" LATENCY="0" OPTYPE="add" PRAGMA="" RTLNAME="add_ln261_fu_1417_p2" SOURCE="can.c:261" VARIABLE="add_ln261" MODULE="recvFrame_logic_1" LOOP="" BUNDLEDNAME="" DSP="0" BRAM="0" URAM="0"/>
	<BindNode BINDTYPE="op" DISPLAY="bind_op add" ID="" IMPL="fabric" LATENCY="0" OPTYPE="add" PRAGMA="" RTLNAME="add_ln257_fu_1429_p2" SOURCE="can.c:257" VARIABLE="add_ln257" MODULE="recvFrame_logic_1" LOOP="" BUNDLEDNAME="" DSP="0" BRAM="0" URAM="0"/>
	<BindNode BINDTYPE="op" DISPLAY="bind_op add" ID="" IMPL="fabric" LATENCY="0" OPTYPE="add" PRAGMA="" RTLNAME="add_ln253_fu_1441_p2" SOURCE="can.c:253" VARIABLE="add_ln253" MODULE="recvFrame_logic_1" LOOP="" BUNDLEDNAME="" DSP="0" BRAM="0" URAM="0"/>
	<BindNode BINDTYPE="op" DISPLAY="bind_op add" ID="" IMPL="fabric" LATENCY="0" OPTYPE="add" PRAGMA="" RTLNAME="add_ln269_fu_1453_p2" SOURCE="can.c:269" VARIABLE="add_ln269" MODULE="recvFrame_logic_1" LOOP="" BUNDLEDNAME="" DSP="0" BRAM="0" URAM="0"/>
	<BindNode BINDTYPE="op" DISPLAY="bind_op add" ID="" IMPL="fabric" LATENCY="0" OPTYPE="add" PRAGMA="" RTLNAME="received_can" SOURCE="can.c:280" VARIABLE="add_ln280" MODULE="recvFrame_logic_1" LOOP="" BUNDLEDNAME="" DSP="0" BRAM="0" URAM="0"/>
	<BindNode BINDTYPE="op" DISPLAY="bind_op add" ID="" IMPL="fabric" LATENCY="0" OPTYPE="add" PRAGMA="" RTLNAME="add_ln283_fu_1482_p2" SOURCE="can.c:283" VARIABLE="add_ln283" MODULE="recvFrame_logic_1" LOOP="" BUNDLEDNAME="" DSP="0" BRAM="0" URAM="0"/>
	<BindNode BINDTYPE="op" DISPLAY="bind_op icmp" ID="" IMPL="auto" LATENCY="0" OPTYPE="icmp" PRAGMA="" RTLNAME="icmp_ln378_fu_499_p2" SOURCE="dlin.c:378" VARIABLE="icmp_ln378" MODULE="clu" LOOP="VITIS_LOOP_378_1" BUNDLEDNAME="" DSP="0" BRAM="0" URAM="0"/>
	<BindNode BINDTYPE="op" DISPLAY="bind_op add" ID="" IMPL="fabric" LATENCY="0" OPTYPE="add" PRAGMA="" RTLNAME="lin_nr_2_fu_505_p2" SOURCE="dlin.c:378" VARIABLE="lin_nr_2" MODULE="clu" LOOP="VITIS_LOOP_378_1" BUNDLEDNAME="" DSP="0" BRAM="0" URAM="0"/>
	<BindNode BINDTYPE="op" DISPLAY="bind_op shl" ID="" IMPL="auto_pipe" LATENCY="0" OPTYPE="shl" PRAGMA="" RTLNAME="shl_ln323_fu_515_p2" SOURCE="dlin.c:323" VARIABLE="shl_ln323" MODULE="clu" LOOP="VITIS_LOOP_378_1" BUNDLEDNAME="" DSP="0" BRAM="0" URAM="0"/>
	<BindNode BINDTYPE="op" DISPLAY="bind_op and" ID="" IMPL="auto" LATENCY="0" OPTYPE="and" PRAGMA="" RTLNAME="and_ln323_fu_521_p2" SOURCE="dlin.c:323" VARIABLE="and_ln323" MODULE="clu" LOOP="VITIS_LOOP_378_1" BUNDLEDNAME="" DSP="0" BRAM="0" URAM="0"/>
	<BindNode BINDTYPE="op" DISPLAY="bind_op icmp" ID="" IMPL="auto" LATENCY="0" OPTYPE="icmp" PRAGMA="" RTLNAME="icmp_ln323_fu_526_p2" SOURCE="dlin.c:323" VARIABLE="icmp_ln323" MODULE="clu" LOOP="VITIS_LOOP_378_1" BUNDLEDNAME="" DSP="0" BRAM="0" URAM="0"/>
	<BindNode BINDTYPE="op" DISPLAY="bind_op add" ID="" IMPL="fabric" LATENCY="0" OPTYPE="add" PRAGMA="" RTLNAME="linbase_mod_fu_544_p2" SOURCE="dlin.c:325" VARIABLE="linbase_mod" MODULE="clu" LOOP="VITIS_LOOP_378_1" BUNDLEDNAME="" DSP="0" BRAM="0" URAM="0"/>
	<BindNode BINDTYPE="op" DISPLAY="bind_op icmp" ID="" IMPL="auto" LATENCY="0" OPTYPE="icmp" PRAGMA="" RTLNAME="icmp_ln337_fu_563_p2" SOURCE="can.c:337" VARIABLE="icmp_ln337" MODULE="clu" LOOP="VITIS_LOOP_337_1" BUNDLEDNAME="" DSP="0" BRAM="0" URAM="0"/>
	<BindNode BINDTYPE="op" DISPLAY="bind_op add" ID="" IMPL="fabric" LATENCY="0" OPTYPE="add" PRAGMA="" RTLNAME="add_ln337_fu_569_p2" SOURCE="can.c:337" VARIABLE="add_ln337" MODULE="clu" LOOP="VITIS_LOOP_337_1" BUNDLEDNAME="" DSP="0" BRAM="0" URAM="0"/>
	<BindNode BINDTYPE="op" DISPLAY="bind_op shl" ID="" IMPL="auto_pipe" LATENCY="0" OPTYPE="shl" PRAGMA="" RTLNAME="shl_ln301_fu_579_p2" SOURCE="can.c:301" VARIABLE="shl_ln301" MODULE="clu" LOOP="VITIS_LOOP_337_1" BUNDLEDNAME="" DSP="0" BRAM="0" URAM="0"/>
	<BindNode BINDTYPE="op" DISPLAY="bind_op and" ID="" IMPL="auto" LATENCY="0" OPTYPE="and" PRAGMA="" RTLNAME="and_ln301_fu_585_p2" SOURCE="can.c:301" VARIABLE="and_ln301" MODULE="clu" LOOP="VITIS_LOOP_337_1" BUNDLEDNAME="" DSP="0" BRAM="0" URAM="0"/>
	<BindNode BINDTYPE="op" DISPLAY="bind_op icmp" ID="" IMPL="auto" LATENCY="0" OPTYPE="icmp" PRAGMA="" RTLNAME="icmp_ln301_fu_590_p2" SOURCE="can.c:301" VARIABLE="icmp_ln301" MODULE="clu" LOOP="VITIS_LOOP_337_1" BUNDLEDNAME="" DSP="0" BRAM="0" URAM="0"/>
	<BindNode BINDTYPE="op" DISPLAY="bind_op add" ID="" IMPL="fabric" LATENCY="0" OPTYPE="add" PRAGMA="" RTLNAME="canaddr_mod_fu_608_p2" SOURCE="can.c:303" VARIABLE="canaddr_mod" MODULE="clu" LOOP="VITIS_LOOP_337_1" BUNDLEDNAME="" DSP="0" BRAM="0" URAM="0"/>
	<BindNode BINDTYPE="op" DISPLAY="bind_op add" ID="" IMPL="fabric" LATENCY="0" OPTYPE="add" PRAGMA="" RTLNAME="add_ln304_fu_623_p2" SOURCE="can.c:304" VARIABLE="add_ln304" MODULE="clu" LOOP="VITIS_LOOP_337_1" BUNDLEDNAME="" DSP="0" BRAM="0" URAM="0"/>
	<BindNode BINDTYPE="op" DISPLAY="bind_op icmp" ID="" IMPL="auto" LATENCY="0" OPTYPE="icmp" PRAGMA="" RTLNAME="icmp_ln306_fu_698_p2" SOURCE="can.c:306" VARIABLE="icmp_ln306" MODULE="clu" LOOP="VITIS_LOOP_337_1" BUNDLEDNAME="" DSP="0" BRAM="0" URAM="0"/>
	<BindNode BINDTYPE="op" DISPLAY="bind_op icmp" ID="" IMPL="auto" LATENCY="0" OPTYPE="icmp" PRAGMA="" RTLNAME="icmp_ln306_1_fu_703_p2" SOURCE="can.c:306" VARIABLE="icmp_ln306_1" MODULE="clu" LOOP="VITIS_LOOP_337_1" BUNDLEDNAME="" DSP="0" BRAM="0" URAM="0"/>
	<BindNode BINDTYPE="op" DISPLAY="bind_op icmp" ID="" IMPL="auto" LATENCY="0" OPTYPE="icmp" PRAGMA="" RTLNAME="icmp_ln306_2_fu_718_p2" SOURCE="can.c:306" VARIABLE="icmp_ln306_2" MODULE="clu" LOOP="VITIS_LOOP_337_1" BUNDLEDNAME="" DSP="0" BRAM="0" URAM="0"/>
	<BindNode BINDTYPE="op" DISPLAY="bind_op select" ID="" IMPL="auto_sel" LATENCY="0" OPTYPE="select" PRAGMA="" RTLNAME="readIndex_fu_724_p3" SOURCE="can.c:308" VARIABLE="readIndex" MODULE="clu" LOOP="VITIS_LOOP_337_1" BUNDLEDNAME="" DSP="0" BRAM="0" URAM="0"/>
	<BindNode BINDTYPE="op" DISPLAY="bind_op select" ID="" IMPL="auto_sel" LATENCY="0" OPTYPE="select" PRAGMA="" RTLNAME="readIndex_2_fu_750_p3" SOURCE="can.c:312" VARIABLE="readIndex_2" MODULE="clu" LOOP="VITIS_LOOP_337_1" BUNDLEDNAME="" DSP="0" BRAM="0" URAM="0"/>
	<BindNode BINDTYPE="adapter" DISPLAY="bind_adapter axilite" ID="" IMPL="" LATENCY="" OPTYPE="" PRAGMA="yes" RTLNAME="EN_s_axi_U" SOURCE="" VARIABLE="" MODULE="clu" LOOP="" BUNDLEDNAME="EN" DSP="0" BRAM="0" URAM="0"/>
	<BindNode BINDTYPE="adapter" DISPLAY="bind_adapter axi_master" ID="" IMPL="" LATENCY="" OPTYPE="" PRAGMA="yes" RTLNAME="can_addr_m_axi_U" SOURCE="" VARIABLE="" MODULE="clu" LOOP="" BUNDLEDNAME="can_addr" DSP="0" BRAM="0" URAM="0"/>
	<BindNode BINDTYPE="adapter" DISPLAY="bind_adapter axi_master" ID="" IMPL="" LATENCY="" OPTYPE="" PRAGMA="yes" RTLNAME="lin_addr_m_axi_U" SOURCE="" VARIABLE="" MODULE="clu" LOOP="" BUNDLEDNAME="lin_addr" DSP="0" BRAM="0" URAM="0"/>
	<BindNode BINDTYPE="adapter" DISPLAY="bind_adapter axi_master" ID="" IMPL="" LATENCY="" OPTYPE="" PRAGMA="yes" RTLNAME="ps_ddr_m_axi_U" SOURCE="" VARIABLE="" MODULE="clu" LOOP="" BUNDLEDNAME="ps_ddr" DSP="0" BRAM="0" URAM="0"/>
</BindInfo>
